{
  "sections": {
    "image_banner": {
      "type": "image-banner",
      "blocks": {
        "heading": {
          "type": "heading",
          "settings": {
            "heading": "Studiocraft is a user-centric independent design studio focusing on simplicity",
            "heading_size": "h1"
          }
        },
        "text": {
          "type": "text",
          "settings": {
            "text": "Experts in our craft—but it's not about us. It's about what happens next.",
            "text_style": "subtitle"
          }
        },
        "button": {
          "type": "buttons",
          "settings": {
            "button_label_1": "Get in Touch",
            "button_link_1": "shopify:\/\/pages\/contact",
            "button_style_secondary_1": false,
            "button_label_2": "Learn more",
            "button_link_2": "shopify:\/\/pages\/services-capabilities",
            "button_style_secondary_2": true
          }
        }
      },
      "block_order": [
        "heading",
        "text",
        "button"
      ],
      "settings": {
        "image": "shopify:\/\/shop_images\/studiocraft-cover.svg",
        "image_overlay_opacity": 0,
        "image_height": "large",
        "desktop_content_position": "middle-center",
        "show_text_box": true,
        "desktop_content_alignment": "center",
        "color_scheme": "inverse",
        "image_behavior": "fixed",
        "mobile_content_alignment": "center",
        "stack_images_on_mobile": false,
        "show_text_below": true
      }
    },
    "rich_text": {
      "type": "rich-text",
      "blocks": {
        "heading": {
          "type": "heading",
          "settings": {
            "heading": "Our focus is not on ourselves, but rather on what lies ahead.",
            "heading_size": "h1"
          }
        },
        "text": {
          "type": "text",
          "settings": {
            "text": "<p>It revolves around the decisions we collectively make, as they will shape our future as a whole. We see, we feel, and we decide. Together we create. Will it be an eco-friendly music record from hemp and sugar? Is it sustainble marketing startegies?<\/p>"
          }
        },
        "button": {
          "type": "button",
          "settings": {
            "button_label": "Let's go",
            "button_link": "shopify:\/\/pages\/contact"
          }
        }
      },
      "block_order": [
        "heading",
        "text",
        "button"
      ],
      "settings": {
        "color_scheme": "default",
        "full_width": true,
        "padding_top": 100,
        "padding_bottom": 100
      }
    },
    "multirow": {
      "type": "multirow",
      "blocks": {
        "row1": {
          "type": "row",
          "settings": {
            "image": "shopify:\/\/shop_images\/graphic-design-creative.svg",
            "caption": "Experts In",
            "heading": "Design & Creative",
            "text": "<p>Pair text with an image to focus on your chosen product, collection, or blog post. Add details on availability, style, or even provide a review.<\/p>",
            "button_label": "Learn more",
            "button_link": "shopify:\/\/pages\/contact"
          }
        },
        "row2": {
          "type": "row",
          "settings": {
            "image": "shopify:\/\/shop_images\/graphic-development-engineering.svg",
            "heading": "Digital Applications & Engineering",
            "text": "<p>Pair text with an image to focus on your chosen product, collection, or blog post. Add details on availability, style, or even provide a review.<\/p>",
            "button_label": "Learn more",
            "button_link": "shopify:\/\/pages\/contact"
          }
        },
        "row3": {
          "type": "row",
          "settings": {
            "image": "shopify:\/\/shop_images\/graphic-research-strategy.svg",
            "caption": "Experts In",
            "heading": "Research & Strategy",
            "text": "<p>Pair text with an image to focus on your chosen product, collection, or blog post. Add details on availability, style, or even provide a review.<\/p>",
            "button_label": "Learn more",
            "button_link": "shopify:\/\/pages\/contact"
          }
        }
      },
      "block_order": [
        "row1",
        "row2",
        "row3"
      ],
      "settings": {
        "image_height": "adapt",
        "desktop_image_width": "medium",
        "heading_size": "h1",
        "text_style": "subtitle",
        "button_style": "primary",
        "desktop_content_position": "middle",
        "desktop_content_alignment": "left",
        "section_color_scheme": "subdued",
        "row_color_scheme": "default",
        "padding_top": 100,
        "padding_bottom": 100
      }
    }
  },
  "order": [
    "image_banner",
    "rich_text",
    "multirow"
  ]
}
